arduino_web_inject/__init__.py
arduino_web_inject/main.py
arduino_web_inject/server.py
tests/__init__.py
tests/minify_html_test.py
arduino_web_inject-0.1.43.dist-info/LICENSE
arduino_web_inject-0.1.43.dist-info/METADATA
arduino_web_inject-0.1.43.dist-info/WHEEL
arduino_web_inject-0.1.43.dist-info/entry_points.txt
arduino_web_inject-0.1.43.dist-info/top_level.txt
arduino_web_inject-0.1.43.dist-info/zip-safe
arduino_web_inject-0.1.43.dist-info/RECORD
